MANIFEST.in
README.rst
glcp.py
setup.py
glibcparse/__init__.py
glibcparse/exc.py
glibcparse/parser.py
glibcparse/preprocess.py
glibcparse/tokenize.py
slugger/__init__.py
slugger/exc.py
slugger.egg-info/PKG-INFO
slugger.egg-info/SOURCES.txt
slugger.egg-info/dependency_links.txt
slugger.egg-info/requires.txt
slugger.egg-info/top_level.txt
slugger/languages/__init__.py
slugger/languages/de.py
slugger/languages/default_language.py
slugger/languages/en.py
slugger/localedata/aa_DJ.ttbl.bz2
slugger/localedata/aa_ER.ttbl.bz2
slugger/localedata/aa_ER@saaho.ttbl.bz2
slugger/localedata/aa_ET.ttbl.bz2
slugger/localedata/af_ZA.ttbl.bz2
slugger/localedata/am_ET.ttbl.bz2
slugger/localedata/an_ES.ttbl.bz2
slugger/localedata/ar_AE.ttbl.bz2
slugger/localedata/ar_BH.ttbl.bz2
slugger/localedata/ar_DZ.ttbl.bz2
slugger/localedata/ar_EG.ttbl.bz2
slugger/localedata/ar_IN.ttbl.bz2
slugger/localedata/ar_IQ.ttbl.bz2
slugger/localedata/ar_JO.ttbl.bz2
slugger/localedata/ar_KW.ttbl.bz2
slugger/localedata/ar_LB.ttbl.bz2
slugger/localedata/ar_LY.ttbl.bz2
slugger/localedata/ar_MA.ttbl.bz2
slugger/localedata/ar_OM.ttbl.bz2
slugger/localedata/ar_QA.ttbl.bz2
slugger/localedata/ar_SA.ttbl.bz2
slugger/localedata/ar_SD.ttbl.bz2
slugger/localedata/ar_SY.ttbl.bz2
slugger/localedata/ar_TN.ttbl.bz2
slugger/localedata/ar_YE.ttbl.bz2
slugger/localedata/as_IN.ttbl.bz2
slugger/localedata/ast_ES.ttbl.bz2
slugger/localedata/az_AZ.ttbl.bz2
slugger/localedata/be_BY.ttbl.bz2
slugger/localedata/be_BY@latin.ttbl.bz2
slugger/localedata/bem_ZM.ttbl.bz2
slugger/localedata/ber_DZ.ttbl.bz2
slugger/localedata/ber_MA.ttbl.bz2
slugger/localedata/bg_BG.ttbl.bz2
slugger/localedata/bho_IN.ttbl.bz2
slugger/localedata/bn_BD.ttbl.bz2
slugger/localedata/bn_IN.ttbl.bz2
slugger/localedata/bo_CN.ttbl.bz2
slugger/localedata/bo_IN.ttbl.bz2
slugger/localedata/br_FR.ttbl.bz2
slugger/localedata/br_FR@euro.ttbl.bz2
slugger/localedata/brx_IN.ttbl.bz2
slugger/localedata/bs_BA.ttbl.bz2
slugger/localedata/byn_ER.ttbl.bz2
slugger/localedata/ca_AD.ttbl.bz2
slugger/localedata/ca_ES.ttbl.bz2
slugger/localedata/ca_ES@euro.ttbl.bz2
slugger/localedata/ca_FR.ttbl.bz2
slugger/localedata/ca_IT.ttbl.bz2
