Metadata-Version: 1.0
Name: slugger
Version: 0.1
Summary: Slugging done right. Tries to support close to 300
Home-page: http://github.com/mbr/slugger
Author: Marc Brinkmann
Author-email: git@marcbrinkmann.de
License: LGPL
Keywords: slug slugging web i18n
Platform: UNKNOWN
Classifier: Development Status :: 4 - Beta
Classifier: Environment :: Web Environment
Classifier: Intended Audience :: Developers
Classifier: License :: OSI Approved :: GNU Library or Lesser General Public License (LGPL)
Classifier: Operating System :: OS Independent
Classifier: Topic :: Internet
Classifier: Topic :: Internet :: WWW/HTTP :: Dynamic Content :: CGI Tools/Libraries
Classifier: Topic :: Software Development :: Internationalization
